clip_video_encode/__init__.py
clip_video_encode/cli.py
clip_video_encode/clip_video_encode.py
clip_video_encode/distributed.py
clip_video_encode/live_numpy_encoder.py
clip_video_encode/reader.py
clip_video_encode/simplemapper.py
clip_video_encode/utils.py
clip_video_encode/writer.py
clip_video_encode/dataset/__init__.py
clip_video_encode/dataset/create_shards.py
clip_video_encode/dataset/dataset_reader.py
clip_video_encode/dataset/kinetics700_example_process.py
clip_video_encode-1.3.0.data/data/README.md
clip_video_encode-1.3.0.dist-info/LICENSE
clip_video_encode-1.3.0.dist-info/METADATA
clip_video_encode-1.3.0.dist-info/WHEEL
clip_video_encode-1.3.0.dist-info/entry_points.txt
clip_video_encode-1.3.0.dist-info/top_level.txt
clip_video_encode-1.3.0.dist-info/RECORD
