Metadata-Version: 2.1
Name: clip-video-encode
Version: 1.3.0
Summary: Easily compute clip embeddings from video frames
Home-page: https://github.com/iejMac/clip-video-encode
Author: Maciej Kilian
Author-email: kilianmaciej6@gmail.com
License: MIT
Keywords: machine learning
Platform: UNKNOWN
Classifier: Development Status :: 4 - Beta
Classifier: Intended Audience :: Developers
Classifier: Topic :: Scientific/Engineering :: Artificial Intelligence
Classifier: License :: OSI Approved :: MIT License
Classifier: Programming Language :: Python :: 3.6
Requires-Dist: tqdm (<5,>=4.62.3)
Requires-Dist: torch (<2,>=1.7.1)
Requires-Dist: numpy (<2,>=1.19.5)
Requires-Dist: webdataset (<0.2,>=0.1.103)
Requires-Dist: fire (<0.5.0,>=0.4.0)
Requires-Dist: torchvision (<2,>=0.10.1)
Requires-Dist: open-clip-torch (<3.0.0,>=2.0.0)
Requires-Dist: ffmpeg
Requires-Dist: opencv-python
Requires-Dist: youtube-dl
Requires-Dist: video2numpy (==2.3.0)
Requires-Dist: fsspec (==2022.1.0)
Requires-Dist: pyarrow (<8,>=6.0.1)
Requires-Dist: pandas (<2,>=1.1.5)
